LICENSE
README.md
manifest.json
server/__init__.py
server/__main__.py
server/main.py
huoshui_file_search-1.0.3.dist-info/METADATA
huoshui_file_search-1.0.3.dist-info/WHEEL
huoshui_file_search-1.0.3.dist-info/entry_points.txt
huoshui_file_search-1.0.3.dist-info/licenses/LICENSE
huoshui_file_search-1.0.3.dist-info/RECORD
