Metadata-Version: 2.4
Name: huoshui-file-search
Version: 1.0.3
Summary: Fast file search MCP server for macOS using mdfind command
Project-URL: Homepage, https://github.com/huoshuiai/huoshui-file-search
Project-URL: Repository, https://github.com/huoshuiai/huoshui-file-search
Project-URL: Issues, https://github.com/huoshuiai/huoshui-file-search/issues
Author-email: Huoshui AI <support@huoshui.com>
License: MIT
License-File: LICENSE
Keywords: dxt,file-search,macos,mcp,mdfind,spotlight
Classifier: Development Status :: 4 - Beta
Classifier: Intended Audience :: Developers
Classifier: License :: OSI Approved :: MIT License
Classifier: Operating System :: MacOS :: MacOS X
Classifier: Programming Language :: Python :: 3
Classifier: Programming Language :: Python :: 3.10
Classifier: Programming Language :: Python :: 3.11
Classifier: Programming Language :: Python :: 3.12
Classifier: Topic :: Software Development :: Libraries :: Python Modules
Classifier: Topic :: System :: Filesystems
Requires-Python: >=3.10
Requires-Dist: fastmcp>=0.1.0
Requires-Dist: pydantic>=2.0.0
